spark_jdbc_reader/__init__.py
spark_jdbc_reader/exceptions.py
spark_jdbc_reader/reader.py
spark_jdbc_reader-1.0.3.dist-info/licenses/LICENSE
tests/__init__.py
tests/test_reader.py
spark_jdbc_reader-1.0.3.dist-info/METADATA
spark_jdbc_reader-1.0.3.dist-info/WHEEL
spark_jdbc_reader-1.0.3.dist-info/top_level.txt
spark_jdbc_reader-1.0.3.dist-info/RECORD
