Metadata-Version: 2.4
Name: spark-jdbc-reader
Version: 1.0.3
Summary: A lightweight JDBC table and query reader for PySpark.
Author: Adhi
Author-email: adhiyaman1705@gmail.com
Requires-Python: >=3.7
License-File: LICENSE
Requires-Dist: pyspark>=3.0.0
Dynamic: author
Dynamic: author-email
Dynamic: description
Dynamic: description-content-type
Dynamic: license-file
Dynamic: requires-dist
Dynamic: requires-python
Dynamic: summary
